prodimopy/__init__.py
prodimopy/compare.py
prodimopy/grid.py
prodimopy/hitran.py
prodimopy/movie.py
prodimopy/plot.py
prodimopy/plot_casasim.py
prodimopy/plot_mc.py
prodimopy/plot_models.py
prodimopy/plot_slab.py
prodimopy/postprocessing.py
prodimopy/read.py
prodimopy/read_casasim.py
prodimopy/read_mc.py
prodimopy/read_slab.py
prodimopy/run_slab.py
prodimopy/script_compare.py
prodimopy/script_cpforrestart.py
prodimopy/script_params.py
prodimopy/script_plot.py
prodimopy/script_plot_models.py
prodimopy/script_runprodimo.py
prodimopy/utils.py
prodimopy/utils_casasim.py
prodimopy/chemistry/__init__.py
prodimopy/chemistry/network.py
prodimopy/interface1D/__init__.py
prodimopy/interface1D/infile.py
prodimopy/interface1D/twoppToProDiMo.py
prodimopy/interface2D/__init__.py
prodimopy/interface2D/infile.py
prodimopy/stylelib/prodimopy.mplstyle
prodimopy/stylelib/prodimopy_nb.mplstyle
prodimopy-2.5.1.dist-info/licenses/LICENSE
prodimopy-2.5.1.dist-info/METADATA
prodimopy-2.5.1.dist-info/WHEEL
prodimopy-2.5.1.dist-info/entry_points.txt
prodimopy-2.5.1.dist-info/top_level.txt
prodimopy-2.5.1.dist-info/RECORD
